setup.py
WebTestRecorder.egg-info/PKG-INFO
WebTestRecorder.egg-info/SOURCES.txt
WebTestRecorder.egg-info/dependency_links.txt
WebTestRecorder.egg-info/entry_points.txt
WebTestRecorder.egg-info/not-zip-safe
WebTestRecorder.egg-info/requires.txt
WebTestRecorder.egg-info/top_level.txt
webtestrecorder/__init__.py
webtestrecorder/apachelog.py
webtestrecorder/http.py
webtestrecorder/tests/__init__.py
webtestrecorder/tests/test_recorder.py