Metadata-Version: 1.0
Name: WebTestRecorder
Version: 0.1
Summary: Record activity from a WSGI application, and generate WebTest tests from that record
Home-page: http://pythonpaste.org/webtestrecorder/
Author: Ian Bicking
Author-email: ianb@colorstudy.com
License: MIT
Keywords: wsgi testing unittest doctest webtest
Platform: UNKNOWN
Classifier: Development Status :: 4 - Beta
Classifier: Environment :: Web Environment
Classifier: License :: OSI Approved :: MIT License
Classifier: Topic :: Internet :: WWW/HTTP :: WSGI
Classifier: Topic :: Internet :: WWW/HTTP :: WSGI :: Middleware
Classifier: Topic :: Software Development :: Testing
